ray/__init__.py
ray/actions.py
ray/api.py
ray/application.py
ray/authentication.py
ray/endpoint.py
ray/exceptions.py
ray/hooks.py
ray/http.py
ray/login.py
ray/model.py
ray/shield.py
ray/single_request.py
ray/wsgi/__init__.py
ray/wsgi/wsgi.py
ray_framework-0.2.0.dist-info/DESCRIPTION.rst
ray_framework-0.2.0.dist-info/METADATA
ray_framework-0.2.0.dist-info/RECORD
ray_framework-0.2.0.dist-info/WHEEL
ray_framework-0.2.0.dist-info/metadata.json
ray_framework-0.2.0.dist-info/top_level.txt
