Metadata-Version: 2.0
Name: ray-framework
Version: 0.2.0
Summary:     Ray is a framework that helps you to deliver
Home-page: http://github.com/felipevolpone/ray
Author: Felipe Volpone
Author-email: felipevolpone@gmail.com
License: MIT
Keywords: python framework ray api rest
Platform: UNKNOWN
Classifier: Development Status :: 3 - Alpha
Classifier: Topic :: Utilities
Requires-Dist: PyJWT
Requires-Dist: bottle
Requires-Dist: future
Requires-Dist: pycrypto
